{"T+9QQkK/qszEsgerRE7PfA==":"img-4642-961x1280.jpg","qfotFbjFRkJITAW8G/FXSQ==":"img-4624-1256x1672.jpg","4YqAYsX2LsiezDY8ugy9BQ==":"logo-98x98.png","P+iaHVoXVe0hQqtj3pzTgg==":"img-4722-961x1280.jpg","n1dx+NZv3qks526xC0hZ5Q==":"background13.jpg","oRykAiO0rUD++7AmPeEwUg==":"background1.jpg","OghlLupGE3C2shM9NTl6yw==":"img-4635-961x1280.jpg","iIH7zJ3cnUawvHbYTU1IFg==":"img-4670-961x1280.jpg","6nK7Gk1ynpjLxv4r/VdBBQ==":"img-4709-961x1280.jpg","MNOR3/RRLp9nin+8x4eGnQ==":"img-4646-961x1280.jpg","a9tsE7pRMMXaaqBG1ppW1Q==":"img-8912-1036x1379.jpg","MQG9f6lEqvh5lEX5LcE9qw==":"img-4624-1036x1379.jpg","cHoR7esfNESp9NqSvSUyGg==":"img-9153-1036x1379.jpeg","SRsArotJ6YE8+QNRkmR1nw==":"img-4624-1036x1379.jpeg","CnrPZFv8hOo/GssKABI4fQ==":"img-4667-961x1280.jpg"}